{
  "id": "PC_09",
  "名称": "合同全生命周期管理方案",
  "版本": "v1",
  "状态": "草稿",
  "来源": {
    "类型": "手工创建",
    "来源文件": "2022版首次介绍_制造业V2.1.pptx / 【天工】制造业PPT_首次介绍V5.0-通用材料.pptx",
    "提取时间": "2026-03-24"
  },
  "对应业务卡": ["SC_09"],
  "来源SC方案结构": {
    "SC_ID": "SC_09",
    "描述": "框架协议落地方案 — 框架调用率低、每次重谈重审批的问题解决"
  },
  "业务流程说明": "合同从创建到归档的全生命周期管理，含三种合同类型（单笔/框架协议/合作协议）、在线/线下签署、合同变更与履约执行监控。",
  "适用条件": {
    "行业": ["汽车/汽配", "家电/电子/高科技", "装备制造", "化工冶金", "食品饮料"],
    "物料属性": ["关键品", "杠杆品", "标准品"],
    "权力结构": ["强势买方", "对等博弈"],
    "协同成熟度": ["中", "高"]
  },
  "业务流程": [
    {
      "步骤": 1,
      "业务动作": "合同模板定义（合作方/标的物/条款自动替换）",
      "责任方": "采购管理员",
      "说明": "按品类配置合同模板，固化条款结构"
    },
    {
      "步骤": 2,
      "业务动作": "合同生成/创建（可对接寻源结果自动填入）",
      "责任方": "采购员",
      "说明": "从寻源结果（中标价格/供应商/物料）自动带出合同要素"
    },
    {
      "步骤": 3,
      "业务动作": "合同确认（供应商在线反馈修改意见）",
      "责任方": "供应商 / 采购员",
      "说明": "双方在线协商条款，修改留痕"
    },
    {
      "步骤": 4,
      "业务动作": "合同审核（内部审批流）",
      "责任方": "采购员 / 领导",
      "说明": "可比对各版本结构化数据差异；对接OA审批"
    },
    {
      "步骤": 5,
      "业务动作": "合同签署（电子签章 or 线下签署）",
      "责任方": "采购方 / 供应商",
      "说明": "电子签章：支持多家服务商（e签宝/法大大）；线下：上传签章扫描件归档"
    },
    {
      "步骤": 6,
      "业务动作": "合同归档",
      "责任方": "系统自动",
      "说明": "签章完成后自动归档；支持合同版本管理"
    },
    {
      "步骤": 7,
      "业务动作": "合同履约执行",
      "责任方": "采购方 / 供应商",
      "说明": "单笔合同：自动生成订单；框架协议：按调用规则生成采购申请/订单"
    },
    {
      "步骤": 8,
      "业务动作": "合同变更/补充协议",
      "责任方": "采购员 / 供应商",
      "说明": "大变更走合同变更流程，小变更签补充协议"
    },
    {
      "步骤": 9,
      "业务动作": "合同到期提醒与终止",
      "责任方": "系统自动",
      "说明": "到期前自动提醒；终止后供应商权限自动回收"
    }
  ],
  "系统流程方案": [
    {
      "对应业务步骤": 1,
      "系统动作": "管理员配置合同模板，定义合作方、标的物、合同条款的可替换字段",
      "触发模块": "合同管理 - 合同模板管理",
      "输出物": "合同模板",
      "后续触发": "采购员创建合同时引用模板",
      "二开": false
    },
    {
      "对应业务步骤": 2,
      "系统动作": "采购员引用寻源结果（中标供应商/价格/物料）生成合同，系统自动填充模板字段",
      "触发模块": "合同管理 - 合同生成",
      "输出物": "合同草稿",
      "后续触发": "发给供应商确认",
      "二开": false
    },
    {
      "对应业务步骤": 3,
      "系统动作": "供应商在线查看合同内容，反馈修改意见；采购员根据反馈调整",
      "触发模块": "合同管理 - 合同确认",
      "输出物": "合同确认记录（含修改意见）",
      "后续触发": "进入审核流",
      "二开": false
    },
    {
      "对应业务步骤": 4,
      "系统动作": "合同进入审批流，审批人可查看合同版本间结构化数据差异",
      "触发模块": "合同管理 - 合同审核（对接OA）",
      "输出物": "审批记录",
      "后续触发": "审批通过后进入签署环节",
      "二开": false
    },
    {
      "对应业务步骤": 5,
      "系统动作": "电子签章：双方授权人在线签署；支持静默签/双向签/单边签多种模式",
      "触发模块": "合同管理 - 电子签章（e签宝/法大大）",
      "输出物": "已签署合同",
      "后续触发": "自动归档",
      "二开": false
    },
    {
      "对应业务步骤": 6,
      "系统动作": "电子签章完成自动归档；线下签署上传扫描件归档",
      "触发模块": "合同管理 - 合同归档",
      "输出物": "归档合同（含版本记录）",
      "后续触发": "合同进入执行态",
      "二开": false
    },
    {
      "对应业务步骤": 7,
      "系统动作": "单笔合同：审核通过自动生成订单；框架协议：按框架条款（价格/配额）生成采购申请/订单",
      "触发模块": "合同管理 - 合同转订单",
      "输出物": "采购订单 / 采购申请",
      "后续触发": "订单进入协同执行",
      "二开": false
    },
    {
      "对应业务步骤": 8,
      "系统动作": "采购员发起合同变更申请，变更内容与原合同形成版本对比记录",
      "触发模块": "合同管理 - 合同变更",
      "输出物": "变更记录 + 新合同版本",
      "后续触发": "变更审核+签署",
      "二开": false
    },
    {
      "对应业务步骤": 9,
      "系统动作": "合同到期前自动发送提醒；到期后按预设规则自动冻结供应商相关业务权限",
      "触发模块": "合同管理 - 到期提醒",
      "输出物": "到期提醒通知",
      "后续触发": "续签或终止",
      "二开": false
    }
  ],
  "产品功能组合": [
    {
      "功能": "合同模板管理",
      "套件": "S3 - 寻源套件",
      "角色": "主要",
      "配置项": ["合同模板定义（标的物/合作方/条款字段）", "按品类绑定不同模板"],
      "二开介入": false
    },
    {
      "功能": "合同生成/创建",
      "套件": "S3 - 寻源套件",
      "角色": "主要",
      "配置项": ["寻源结果自动带出合同要素"],
      "二开介入": false
    },
    {
      "功能": "合同确认（在线协商）",
      "套件": "S3 - 寻源套件",
      "角色": "主要",
      "配置项": ["确认流程配置"],
      "二开介入": false
    },
    {
      "功能": "合同审核（OA对接）",
      "套件": "S3 - 寻源套件",
      "角色": "主要",
      "配置项": ["审批流配置", "版本差异对比展示"],
      "二开介入": false
    },
    {
      "功能": "电子签章",
      "套件": "S3 - 寻源套件",
      "角色": "主要",
      "配置项": ["签章服务商对接（e签宝/法大大）", "签章授权模式（静默签/双向签/单边签）"],
      "二开介入": false
    },
    {
      "功能": "合同归档",
      "套件": "S3 - 寻源套件",
      "角色": "支撑",
      "配置项": ["版本管理策略"],
      "二开介入": false
    },
    {
      "功能": "合同变更",
      "套件": "S3 - 寻源套件",
      "角色": "支撑",
      "配置项": ["变更审批流配置"],
      "二开介入": false
    },
    {
      "功能": "合同转订单",
      "套件": "S3 - 寻源套件",
      "角色": "主要",
      "配置项": ["单笔合同自动转订单规则", "框架协议调用规则（价格/配额取价逻辑）"],
      "二开介入": false
    },
    {
      "功能": "合同到期提醒",
      "套件": "S3 - 寻源套件",
      "角色": "支撑",
      "配置项": ["到期提前提醒天数配置"],
      "二开介入": false
    },
    {
      "功能": "合同数据分析大屏",
      "套件": "S7 - 数据应用",
      "角色": "支撑",
      "配置项": [],
      "二开介入": false
    }
  ],
  "实施步骤": [
    {
      "顺序": 1,
      "步骤": "按品类配置合同模板（单笔合同模板/框架协议模板/合作协议模板）",
      "产品模块": "合同模板管理",
      "前置依赖": "无",
      "二开": false
    },
    {
      "顺序": 2,
      "步骤": "配置电子签章服务商对接（e签宝/法大大）",
      "产品模块": "电子签章",
      "前置依赖": "商务对接完成",
      "二开": false
    },
    {
      "顺序": 3,
      "步骤": "配置合同审核审批流（对接OA）",
      "产品模块": "合同审核",
      "前置依赖": "步骤1",
      "二开": false
    },
    {
      "顺序": 4,
      "步骤": "配置合同变更审批流",
      "产品模块": "合同变更",
      "前置依赖": "步骤1",
      "二开": false
    },
    {
      "顺序": 5,
      "步骤": "配置框架协议调用规则（价格取价逻辑/配额规则）",
      "产品模块": "合同转订单",
      "前置依赖": "步骤1",
      "二开": false
    },
    {
      "顺序": 6,
      "步骤": "配置合同到期提醒规则（提前N天提醒）",
      "产品模块": "合同到期提醒",
      "前置依赖": "步骤1",
      "二开": false
    },
    {
      "顺序": 7,
      "步骤": "配置合同归档规则和版本管理策略",
      "产品模块": "合同归档",
      "前置依赖": "步骤1",
      "二开": false
    },
    {
      "顺序": 8,
      "步骤": "导入存量合同数据，完成初始化",
      "产品模块": "合同模板管理",
      "前置依赖": "步骤1-7",
      "二开": false
    }
  ],
  "二开介入点": [],
  "关键配置项": [
    "合同类型配置：单笔合同 / 框架协议（年度/季度/月度） / 合作协议（战略/质量/保密）",
    "框架协议价格机制：固定价 / 区间价 / 浮动价（关联行情）",
    "框架协议配额规则：数量上限 / 额度上限 / 期限边界",
    "电子签章模式：双向签署 / 静默签署 / 单边签署",
    "合同变更审批流：重大变更（重新审批）/ 一般变更（备案）",
    "到期提醒规则：提前30/15/7天自动提醒"
  ],
  "成功客户": [],
  "关联方案卡": ["PC_08（供应商准入）", "PC_21（寻源定价）"],
  "更新时间": "2026-03-24",
  "维护人": ""
}
